browser_captcha_solver/__init__.py
browser_captcha_solver/cli.py
browser_captcha_solver/server.py
browser_captcha_solver/solver.py
browser_captcha_solver/template_manager.py
browser_captcha_solver-1.0.3.dist-info/licenses/LICENSE
browser_captcha_solver-1.0.3.dist-info/METADATA
browser_captcha_solver-1.0.3.dist-info/WHEEL
browser_captcha_solver-1.0.3.dist-info/entry_points.txt
browser_captcha_solver-1.0.3.dist-info/top_level.txt
browser_captcha_solver-1.0.3.dist-info/RECORD
