Metadata-Version: 2.4
Name: browser-captcha-solver
Version: 1.0.3
Summary: A Python library for browser-based captcha solving
Author-email: xAffan <affanquddus1122@gmail.com>
License: MIT License
Project-URL: Homepage, https://github.com/xAffan/browser-captcha-solver
Project-URL: Bug Tracker, https://github.com/xAffan/browser-captcha-solver/issues
Project-URL: Documentation, https://github.com/xAffan/browser-captcha-solver
Project-URL: Source Code, https://github.com/xAffan/browser-captcha-solver
Keywords: captcha,recaptcha,hcaptcha,browser,automation,solving,web-scraping,bot-protection
Classifier: Development Status :: 5 - Production/Stable
Classifier: Intended Audience :: Developers
Classifier: Topic :: Internet :: WWW/HTTP :: Browsers
Classifier: Topic :: Security
Classifier: Topic :: Software Development :: Libraries :: Python Modules
Classifier: Programming Language :: Python :: 3
Classifier: Programming Language :: Python :: 3.8
Classifier: Programming Language :: Python :: 3.9
Classifier: Programming Language :: Python :: 3.10
Classifier: Programming Language :: Python :: 3.11
Classifier: Programming Language :: Python :: 3.12
Classifier: Operating System :: OS Independent
Requires-Python: >=3.8
License-File: LICENSE
Requires-Dist: requests>=2.25.0
Provides-Extra: dev
Requires-Dist: pytest>=6.0; extra == "dev"
Requires-Dist: pytest-asyncio; extra == "dev"
Requires-Dist: pytest-cov; extra == "dev"
Requires-Dist: black; extra == "dev"
Requires-Dist: flake8; extra == "dev"
Requires-Dist: twine; extra == "dev"
Requires-Dist: wheel; extra == "dev"
Dynamic: license-file
